riffusion/__init__.py
riffusion/riff.py
riffusion_api-0.0.1.dist-info/LICENSE
riffusion_api-0.0.1.dist-info/METADATA
riffusion_api-0.0.1.dist-info/WHEEL
riffusion_api-0.0.1.dist-info/top_level.txt
riffusion_api-0.0.1.dist-info/RECORD
