Metadata-Version: 2.1
Name: riffusion-api
Version: 0.0.1
Summary: A package for the unofficial Riffusion API
Home-page: https://github.com/Jeffman112/riffusion-api
Author: Jeffman112
Author-email: author@example.com
Project-URL: Bug Tracker, https://github.com/Jeffman112/riffusion-api/issues
Classifier: Programming Language :: Python :: 3
Classifier: License :: OSI Approved :: MIT License
Classifier: Operating System :: OS Independent
Requires-Python: >=3.6
License-File: LICENSE
